llama_index/embeddings/clip/__init__.py
llama_index/embeddings/clip/base.py
flying_delta_embeddings_clip-0.1.0.dist-info/METADATA
flying_delta_embeddings_clip-0.1.0.dist-info/WHEEL
flying_delta_embeddings_clip-0.1.0.dist-info/RECORD
