Metadata-Version: 2.1
Name: flying-delta-embeddings-clip
Version: 0.1.0
Summary: llama-index embeddings clip integration
License: MIT
Author: Your Name
Author-email: you@example.com
Requires-Python: >=3.8.1,<3.12
Classifier: License :: OSI Approved :: MIT License
Classifier: Programming Language :: Python :: 3
Classifier: Programming Language :: Python :: 3.9
Classifier: Programming Language :: Python :: 3.10
Classifier: Programming Language :: Python :: 3.11
Requires-Dist: clip (>=0.2.0,<0.3.0)
Requires-Dist: flying-delta-core (>=0.9.32,<0.10.0)
Requires-Dist: pillow (>=10.2.0,<11.0.0)
Requires-Dist: torch (>=2.1.2,<3.0.0)
